cachecontrol/__init__.py
cachecontrol/_cmd.py
cachecontrol/adapter.py
cachecontrol/cache.py
cachecontrol/compat.py
cachecontrol/controller.py
cachecontrol/filewrapper.py
cachecontrol/heuristics.py
cachecontrol/serialize.py
cachecontrol/wrapper.py
cachecontrol/caches/__init__.py
cachecontrol/caches/file_cache.py
cachecontrol/caches/redis_cache.py
CacheControl_ldax-0.12.5.3.dist-info/LICENSE.txt
CacheControl_ldax-0.12.5.3.dist-info/METADATA
CacheControl_ldax-0.12.5.3.dist-info/WHEEL
CacheControl_ldax-0.12.5.3.dist-info/entry_points.txt
CacheControl_ldax-0.12.5.3.dist-info/top_level.txt
CacheControl_ldax-0.12.5.3.dist-info/RECORD
